README.md
setup.cfg
setup.py
pyserializer/__init__.py
pyserializer/constants.py
pyserializer/exceptions.py
pyserializer/fields.py
pyserializer/serializers.py
pyserializer/utils.py
pyserializer/validators.py
pyserializer.egg-info/PKG-INFO
pyserializer.egg-info/SOURCES.txt
pyserializer.egg-info/dependency_links.txt
pyserializer.egg-info/requires.txt
pyserializer.egg-info/top_level.txt