Metadata-Version: 1.1
Name: pyserializer
Version: 0.9.1
Summary: Simple python serialization library.
Home-page: UNKNOWN
Author: LocalMed
Author-email: ecordell@localmed.com, pete@localmed.com, joeljames1985@gmail.com
License: MIT
Platform: UNKNOWN
Classifier: Development Status :: 3 - Alpha
Classifier: Environment :: Web Environment
Classifier: Intended Audience :: Developers
Classifier: License :: OSI Approved :: MIT License
Classifier: Operating System :: OS Independent
Classifier: Programming Language :: Python :: 2.7
Classifier: Programming Language :: Python :: 3.3
Classifier: Programming Language :: Python :: 3.4
Classifier: Programming Language :: Python :: 3.5
Classifier: Topic :: Internet :: WWW/HTTP
